mdsci/__init__.py
mdsci/cli.py
mdsci/core.py
mdsci/decorators.py
mdsci/main_filter.py
mdsci/svgs.py
mdsci/filters/__init__.py
mdsci/filters/color.py
mdsci/styles/__init__.py
mdsci/styles/mdsci.css
mdsci-0.0.2.dist-info/licenses/LICENSE
mdsci-0.0.2.dist-info/METADATA
mdsci-0.0.2.dist-info/WHEEL
mdsci-0.0.2.dist-info/entry_points.txt
mdsci-0.0.2.dist-info/top_level.txt
mdsci-0.0.2.dist-info/RECORD
