Metadata-Version: 2.4
Name: mdsci
Version: 0.0.2
Summary: Extended Markdown syntax for scientific writing
Author: wklchris
License-Expression: MIT
Project-URL: Homepage, https://github.com/wklchris/mdsci
Classifier: Programming Language :: Python :: 3
Requires-Python: >=3.8
License-File: LICENSE
Requires-Dist: pandocfilters>=1.5
Dynamic: license-file
